astronomer_providers-1.19.4-py3.12-nspkg.pth
astronomer/providers/package.py
astronomer/providers/amazon/__init__.py
astronomer/providers/amazon/aws/__init__.py
astronomer/providers/amazon/aws/example_dags/__init__.py
astronomer/providers/amazon/aws/example_dags/example_aws_nuke.py
astronomer/providers/amazon/aws/example_dags/example_batch.py
astronomer/providers/amazon/aws/example_dags/example_emr_eks_containers_job.py
astronomer/providers/amazon/aws/example_dags/example_emr_sensor.py
astronomer/providers/amazon/aws/example_dags/example_redshift_cluster_management.py
astronomer/providers/amazon/aws/example_dags/example_redshift_data.py
astronomer/providers/amazon/aws/example_dags/example_redshift_sql.py
astronomer/providers/amazon/aws/example_dags/example_s3.py
astronomer/providers/amazon/aws/example_dags/example_sagemaker.py
astronomer/providers/amazon/aws/extractors/__init__.py
astronomer/providers/amazon/aws/extractors/redshift.py
astronomer/providers/amazon/aws/hooks/__init__.py
astronomer/providers/amazon/aws/hooks/aws_logs.py
astronomer/providers/amazon/aws/hooks/base_aws.py
astronomer/providers/amazon/aws/hooks/base_aws_async.py
astronomer/providers/amazon/aws/hooks/batch_client.py
astronomer/providers/amazon/aws/hooks/emr.py
astronomer/providers/amazon/aws/hooks/redshift_cluster.py
astronomer/providers/amazon/aws/hooks/redshift_data.py
astronomer/providers/amazon/aws/hooks/redshift_sql.py
astronomer/providers/amazon/aws/hooks/s3.py
astronomer/providers/amazon/aws/hooks/sagemaker.py
astronomer/providers/amazon/aws/operators/__init__.py
astronomer/providers/amazon/aws/operators/batch.py
astronomer/providers/amazon/aws/operators/emr.py
astronomer/providers/amazon/aws/operators/redshift_cluster.py
astronomer/providers/amazon/aws/operators/redshift_data.py
astronomer/providers/amazon/aws/operators/redshift_sql.py
astronomer/providers/amazon/aws/operators/sagemaker.py
astronomer/providers/amazon/aws/sensors/__init__.py
astronomer_providers-1.19.4.dist-info/METADATA
astronomer_providers-1.19.4.dist-info/WHEEL
astronomer_providers-1.19.4.dist-info/entry_points.txt
astronomer_providers-1.19.4.dist-info/namespace_packages.txt
astronomer_providers-1.19.4.dist-info/top_level.txt
astronomer_providers-1.19.4.dist-info/RECORD
