Metadata-Version: 2.1
Name: astronomer-providers
Version: 1.19.4
Summary: Apache Airflow Providers containing Deferrable Operators & Sensors from Astronomer
Home-page: https://github.com/astronomer/astronomer-providers/
Author: Astronomer
Author-email: humans@astronomer.io
License: Apache License 2.0
Project-URL: Source Code, https://github.com/astronomer/astronomer-providers/
Project-URL: Homepage, https://astronomer.io/
Project-URL: Documentation, https://astronomer-providers.rtfd.io/
Project-URL: Changelog, https://github.com/astronomer/astronomer-providers/blob/main/CHANGELOG.rst
Classifier: Development Status :: 5 - Production/Stable
Classifier: Environment :: Web Environment
Classifier: Framework :: Apache Airflow
Classifier: Framework :: Apache Airflow :: Provider
Classifier: Intended Audience :: Developers
Classifier: License :: OSI Approved :: Apache Software License
Classifier: Operating System :: OS Independent
Classifier: Programming Language :: Python
Classifier: Programming Language :: Python :: 3
Classifier: Programming Language :: Python :: 3.8
Classifier: Programming Language :: Python :: 3.9
Classifier: Programming Language :: Python :: 3.10
Classifier: Programming Language :: Python :: 3.11
Requires-Python: >=3.8
Requires-Dist: apache-airflow>=2.6.0
Requires-Dist: Flask-Session<0.6.0
Requires-Dist: aiohttp
Requires-Dist: aiofiles
Requires-Dist: asgiref
Requires-Dist: markupsafe>=1.1.1
Provides-Extra: all
Requires-Dist: aiobotocore>=2.1.1; extra == "all"
Requires-Dist: apache-airflow-providers-amazon>=8.18.0; extra == "all"
Requires-Dist: apache-airflow-providers-apache-hive>=6.1.5; extra == "all"
Requires-Dist: apache-airflow-providers-apache-livy>=3.7.1; extra == "all"
Requires-Dist: apache-airflow-providers-cncf-kubernetes>=8.0.0; extra == "all"
Requires-Dist: apache-airflow-providers-databricks>=6.1.0; extra == "all"
Requires-Dist: apache-airflow-providers-google>=10.15.0; extra == "all"
Requires-Dist: apache-airflow-providers-http>=4.9.0; extra == "all"
Requires-Dist: apache-airflow-providers-snowflake>=5.3.0; extra == "all"
Requires-Dist: apache-airflow-providers-sftp>=4.9.0; extra == "all"
Requires-Dist: apache-airflow-providers-microsoft-azure>=9.0.0; extra == "all"
Requires-Dist: asyncssh>=2.12.0; extra == "all"
Requires-Dist: apache-airflow-providers-dbt-cloud>=3.5.1; extra == "all"
Requires-Dist: gcloud-aio-bigquery; extra == "all"
Requires-Dist: gcloud-aio-storage; extra == "all"
Requires-Dist: kubernetes-asyncio; extra == "all"
Requires-Dist: impyla; extra == "all"
Requires-Dist: openlineage-airflow>=0.12.0; extra == "all"
Requires-Dist: paramiko; extra == "all"
Requires-Dist: snowflake-sqlalchemy>=1.4.4; extra == "all"
Requires-Dist: databricks-sql-connector>=2.0.4; python_version >= "3.10" and extra == "all"
Provides-Extra: amazon
Requires-Dist: apache-airflow-providers-amazon>=8.18.0; extra == "amazon"
Requires-Dist: aiobotocore>=2.1.1; extra == "amazon"
Provides-Extra: apache.hive
Requires-Dist: apache-airflow-providers-apache-hive>=6.1.5; extra == "apache-hive"
Requires-Dist: impyla; extra == "apache-hive"
Provides-Extra: apache.livy
Requires-Dist: apache-airflow-providers-apache-livy>=3.7.1; extra == "apache-livy"
Requires-Dist: paramiko; extra == "apache-livy"
Provides-Extra: cncf.kubernetes
Requires-Dist: apache-airflow-providers-cncf-kubernetes>=8.0.0; extra == "cncf-kubernetes"
Requires-Dist: kubernetes-asyncio; extra == "cncf-kubernetes"
Provides-Extra: databricks
Requires-Dist: apache-airflow-providers-databricks>=6.1.0; extra == "databricks"
Requires-Dist: databricks-sql-connector>=2.0.4; python_version >= "3.10" and extra == "databricks"
Provides-Extra: dbt.cloud
Requires-Dist: apache-airflow-providers-dbt-cloud>=3.5.1; extra == "dbt-cloud"
Provides-Extra: docs
Requires-Dist: sphinx; extra == "docs"
Requires-Dist: sphinx-autoapi; extra == "docs"
Requires-Dist: sphinx-copybutton; extra == "docs"
Requires-Dist: astronomer-providers[all]; extra == "docs"
Provides-Extra: google
Requires-Dist: apache-airflow-providers-google>=10.15.0; extra == "google"
Requires-Dist: gcloud-aio-storage; extra == "google"
Requires-Dist: gcloud-aio-bigquery; extra == "google"
Provides-Extra: http
Requires-Dist: apache-airflow-providers-http>=4.9.0; extra == "http"
Provides-Extra: microsoft.azure
Requires-Dist: apache-airflow-providers-microsoft-azure>=9.0.0; extra == "microsoft-azure"
Provides-Extra: mypy
Requires-Dist: mypy>=0.950; extra == "mypy"
Requires-Dist: types-aiofiles; extra == "mypy"
Requires-Dist: types-boto; extra == "mypy"
Requires-Dist: types-certifi; extra == "mypy"
Requires-Dist: types-croniter; extra == "mypy"
Requires-Dist: types-Deprecated; extra == "mypy"
Requires-Dist: types-docutils; extra == "mypy"
Requires-Dist: types-freezegun; extra == "mypy"
Requires-Dist: types-paramiko; extra == "mypy"
Requires-Dist: types-protobuf; extra == "mypy"
Requires-Dist: types-python-dateutil; extra == "mypy"
Requires-Dist: types-python-slugify; extra == "mypy"
Requires-Dist: types-pytz; extra == "mypy"
Requires-Dist: types-redis; extra == "mypy"
Requires-Dist: types-requests; extra == "mypy"
Requires-Dist: types-setuptools; extra == "mypy"
Requires-Dist: types-termcolor; extra == "mypy"
Requires-Dist: types-tabulate; extra == "mypy"
Requires-Dist: types-toml; extra == "mypy"
Requires-Dist: types-Markdown; extra == "mypy"
Requires-Dist: types-PyMySQL; extra == "mypy"
Requires-Dist: types-PyYAML; extra == "mypy"
Requires-Dist: snowflake-connector-python>=3.3.0; extra == "mypy"
Provides-Extra: openlineage
Requires-Dist: openlineage-airflow>=0.12.0; extra == "openlineage"
Provides-Extra: sftp
Requires-Dist: apache-airflow-providers-sftp>=4.9.0; extra == "sftp"
Requires-Dist: asyncssh>=2.12.0; extra == "sftp"
Provides-Extra: snowflake
Requires-Dist: apache-airflow-providers-snowflake>=5.3.0; extra == "snowflake"
Requires-Dist: snowflake-sqlalchemy>=1.4.4; extra == "snowflake"
Provides-Extra: tests
Requires-Dist: aioresponses; extra == "tests"
Requires-Dist: asynctest; extra == "tests"
Requires-Dist: parameterized; extra == "tests"
Requires-Dist: pytest; extra == "tests"
Requires-Dist: pytest-asyncio; extra == "tests"
Requires-Dist: pytest-cov; extra == "tests"
Requires-Dist: pre-commit; extra == "tests"
